leitor_pdf_sensivel/__init__.py
leitor_pdf_sensivel/elimina_dados_sensiveis.py
leitor_pdf_sensivel/le_arquivo_sem_dados_sensiveis.py
leitor_pdf_sensivel/data/exames.xlsx
leitor_pdf_sensivel-1.4.dist-info/METADATA
leitor_pdf_sensivel-1.4.dist-info/WHEEL
leitor_pdf_sensivel-1.4.dist-info/top_level.txt
leitor_pdf_sensivel-1.4.dist-info/RECORD
